bitclust/__init__.py
bitclust/__main__.py
bitclust-0.0.13.dist-info/METADATA
bitclust-0.0.13.dist-info/WHEEL
bitclust-0.0.13.dist-info/entry_points.txt
bitclust-0.0.13.dist-info/top_level.txt
bitclust-0.0.13.dist-info/RECORD
