Metadata-Version: 2.1
Name: bitclust
Version: 0.0.13
Summary: Fast and memory-efficient clustering of long Molecular Dynamics
Home-page: https://github.com/rglez/bitclust
Author: Roy González-Alemán
Author-email: roy.gonzalez-aleman@u-psud.fr
License: UNKNOWN
Platform: UNKNOWN
Classifier: Programming Language :: Python :: 3
Classifier: Programming Language :: Python :: 3.6
Requires-Dist: bitarray (==1.2.1)
Requires-Dist: numpy
Requires-Dist: pandas
Requires-Dist: matplotlib
